r2/__init__.py
r2/configuration.py
r2/install.py
r2/main.py
r2/actions/__init__.py
r2/actions/action.py
r2/actions/action_dispatcher.py
r2/actions/record/__init__.py
r2/actions/record/record.py
r2/actions/replay/__init__.py
r2/actions/replay/replay.py
r2/core/__init__.py
r2/core/flask_server.py
r2/core/package.py
r2/core/test_package.py
r2/helpers/__init__.py
r2/helpers/constants.py
r2/helpers/server_mode.py
r2-0.4.2.dist-info/METADATA
r2-0.4.2.dist-info/WHEEL
r2-0.4.2.dist-info/entry_points.txt
r2-0.4.2.dist-info/top_level.txt
r2-0.4.2.dist-info/RECORD
