Metadata-Version: 2.1
Name: r2
Version: 0.4.2
Summary: Software 'r2' is designed to record and replay responses (to mock) from REST API services
Home-page: https://github.com/NexSabre/r2
Author: Nex Sabre
Author-email: nexsabre@protonmail.com
License: UNKNOWN
Platform: UNKNOWN
Classifier: Intended Audience :: Developers
Classifier: License :: OSI Approved :: MIT License
Classifier: Natural Language :: English
Classifier: Operating System :: OS Independent
Classifier: Operating System :: MacOS :: MacOS X
Classifier: Operating System :: POSIX :: Linux
Classifier: Operating System :: Microsoft :: Windows
Classifier: Programming Language :: Python
Classifier: Programming Language :: Python :: 3
Classifier: Programming Language :: Python :: 3 :: Only
Classifier: Programming Language :: Python :: 3.6
Classifier: Programming Language :: Python :: 3.7
Classifier: Programming Language :: Python :: 3.8
Requires-Python: >=3.6
Requires-Dist: requests (~=2.24.0)
Requires-Dist: Flask (~=1.1.2)
Requires-Dist: setuptools (~=49.2.0)
Requires-Dist: flask-cors (~=3.0.8)
Requires-Dist: dataclasses (~=0.6)
Requires-Dist: urllib3 (~=1.25.8)
